klaudlytics/__init__.py
klaudlytics/cli.py
klaudlytics/main.py
klaudlytics/config/__init__.py
klaudlytics/modules/__init__.py
klaudlytics/modules/db_optimizer.py
klaudlytics/modules/ec2_optimizer.py
klaudlytics/modules/s3_optimizer.py
klaudlytics/utils/__init__.py
klaudlytics/utils/aws_client.py
klaudlytics/utils/region_utils.py
klaudlytics-0.2.2.dist-info/METADATA
klaudlytics-0.2.2.dist-info/WHEEL
klaudlytics-0.2.2.dist-info/entry_points.txt
klaudlytics-0.2.2.dist-info/top_level.txt
klaudlytics-0.2.2.dist-info/RECORD
