Metadata-Version: 2.1
Name: klaudlytics
Version: 0.2.2
Summary: Cloud cost optimization tool
Home-page: https://github.com/geek0ps/klaudlytics
Author: Omoleye Julius
Author-email: julius.omoleye@outlook.com
Classifier: Programming Language :: Python :: 3
Classifier: License :: OSI Approved :: MIT License
Classifier: Operating System :: OS Independent
Requires-Python: >=3.6
Requires-Dist: boto3
Requires-Dist: pyyaml
Requires-Dist: termcolor
